LICENSE
README.md
setup.py
box/__init__.py
box/__main__.py
box/_config.py
box/commit.py
box/exceptions.py
box/filter.py
box/ignore.py
box/tracker.py
box/utils.py
box_vcs.egg-info/PKG-INFO
box_vcs.egg-info/SOURCES.txt
box_vcs.egg-info/dependency_links.txt
box_vcs.egg-info/entry_points.txt
box_vcs.egg-info/requires.txt
box_vcs.egg-info/top_level.txt
tests/test_box.py