Metadata-Version: 2.1
Name: box-vcs
Version: 0.3.0
Summary: Fast, easy-to-use file versioning with Box
Home-page: https://github.com/firlast/box
Author: Firlast
Author-email: firlastinc@gmail.com
License: GNU GPLv2
Keywords: version,control,versioning,vcs
Classifier: License :: OSI Approved :: GNU General Public License v2 (GPLv2)
Classifier: Development Status :: 5 - Production/Stable
Classifier: Intended Audience :: Developers
Classifier: Natural Language :: English
Classifier: Operating System :: Unix
Classifier: Programming Language :: Python :: 3
Classifier: Topic :: Software Development :: Version Control
Requires-Python: >=3.7
License-File: LICENSE
